rfsniffer.py
rpi_rfsniffer-0.1.0.dist-info/DESCRIPTION.rst
rpi_rfsniffer-0.1.0.dist-info/METADATA
rpi_rfsniffer-0.1.0.dist-info/RECORD
rpi_rfsniffer-0.1.0.dist-info/WHEEL
rpi_rfsniffer-0.1.0.dist-info/entry_points.txt
rpi_rfsniffer-0.1.0.dist-info/metadata.json
rpi_rfsniffer-0.1.0.dist-info/top_level.txt
rpi_rfsniffer-0.1.0.dist-info/zip-safe
