Metadata-Version: 2.0
Name: rpi-rfsniffer
Version: 0.1.0
Summary: RF remote sniffer and sender for the Raspberry Pi
Home-page: https://github.com/jderehag/rpi-rfsniffer
Author: Jesper Derehag
Author-email: jderehag@hotmail.com
License: BSD
Keywords: home automation raspberry-pi RPi rf sniffing sending
Platform: UNKNOWN
Classifier: Development Status :: 4 - Beta
Classifier: Intended Audience :: Developers
Classifier: Intended Audience :: End Users/Desktop
Classifier: Topic :: Home Automation
Classifier: Topic :: Terminals :: Serial
Classifier: License :: OSI Approved :: BSD License
Classifier: Programming Language :: Python :: 2.7
Classifier: Programming Language :: Python :: 3
Requires-Dist: RPi.GPIO
Provides-Extra: dev
Requires-Dist: flake8; extra == 'dev'
